book7/__init__.py
book7-0.0.1.dist-info/LICENSE
book7-0.0.1.dist-info/METADATA
book7-0.0.1.dist-info/WHEEL
book7-0.0.1.dist-info/top_level.txt
book7-0.0.1.dist-info/RECORD
