Metadata-Version: 2.1
Name: book7
Version: 0.0.1
Summary: python tools
Home-page: https://github.com/xunull/book7
Author: xunull
Author-email: xunull@163.com
License: UNKNOWN
Platform: UNKNOWN
Classifier: Programming Language :: Python :: 3
Classifier: License :: OSI Approved :: Apache Software License
Classifier: Operating System :: OS Independent
Requires-Python: >=3.0
